submv/__init__.py
submv/_version.py
submv/formats.py
submv/main.py
submv-0.0.1.dist-info/LICENSE
submv-0.0.1.dist-info/METADATA
submv-0.0.1.dist-info/WHEEL
submv-0.0.1.dist-info/entry_points.txt
submv-0.0.1.dist-info/top_level.txt
submv-0.0.1.dist-info/RECORD
