Metadata-Version: 2.1
Name: submv
Version: 0.0.1
Summary: Subtitle shift for resynchronization
Home-page: https://github.com/jorisparet/submv
Author: Joris Paret
Author-email: joris.paret@gmail.com
Maintainer: Joris Paret
License: GPLv3
Keywords: subtitle,sub,srt,shift,move,synchronization,sync
Classifier: License :: OSI Approved :: GNU General Public License v3 (GPLv3)
Classifier: Development Status :: 3 - Alpha
Classifier: Topic :: Utilities 
Classifier: Programming Language :: Python :: 3
Classifier: Operating System :: POSIX :: Linux
Classifier: Operating System :: Microsoft :: Windows
Classifier: Intended Audience :: End Users/Desktop
Classifier: Natural Language :: English
License-File: LICENSE
